{'errorMsg': '', 'data': '{"appId":"k55frqcd","userId":"11634","text":"下班","answer":"","status":"FINISH","action":[],"intentions":[],"params":{},"values":{},"invoker":{"action":"url:/mobile/plugin/siri/ajaxApi.jsp?method=attendance_sign_back","params":{"easstText":"下班","creater":"11634"}},"originText":"下班","intentInfo":{"isSupport":"true","name":"attendance.sign_back","id":"145","title":"签退","isAppIntent":"false"},"easstOauthCode":"HLMnHjufP49NYfLuwqoQ59zX8fKnnOGYVDAMurXpA1fzsqAXchLhmquNcYEZGFdUjrcMn4B3JvBnZQdNFwxNF055CBXrfrhIRzzCYW1ZEKyCtUdqzN3lUts4bhTI0TtSCvVqzxc46Uzy0VkFcUeCzM7gS1ARhQedu9UpoyLQn7M=","encryptParam":false,"intentRecognitionType":"REGEX"}', 'isSuccess': True}